Workbook

Sheet Component Options
A1: P4 — RC Aircraft Bill of Materials: Component Options
A2: Prices include GST, checked 23 Oct 2026. Blue = input from a shop listing or estimate. Stock status as seen on that date.
A4: ID | B4: Component | C4: Option | D4: Product | E4: Key specifications | F4: Unit price (₹) | G4: Stock (23 Oct) | H4: Source | I4: Price basis
A5: TX1 | B5: Transmitter + receiver | C5: 1 | D5: FlySky FS-i6 + FS-iA6B | E5: 6 ch, AFHDS 2A, LCD menu (failsafe, mixing set on the radio) | F5: 4999 | G5: In stock | H5: https://probots.co.in/fs-i6-2-4-ghz-6-channel-remote-radio-controller-for-fpv-quadcopter-tx-rx-mode-2.html | I5: Listing
A6: TX2 | B6: Transmitter + receiver | C6: 2 | D6: FlySky CT6B + FS-R6B | E6: 6 ch, 2.4 GHz GFSK, no LCD — set up from a PC (T6config), 8 × AA | F6: 2413 | G6: In stock | H6: https://st.robu.in/product/ct6b-flysky-2-4ghz-6ch-transmitter-wfs-r6b-receiver-mode-2 | I6: Listing
A7: MO1 | B7: Motor | C7: 1 | D7: A2212 1000 KV outrunner | E7: 3S; 885 g thrust, 15.6 A, 173 W with 1047 prop at 11.1 V (Thingbits table); 52–64 g; 3.17 mm shaft | F7: 383 | G7: In stock | H7: https://st.robu.in/product/a2212-10t-13t-1000kv-brushless-motor-without-soldered-connector | I7: Listing
A8: MO2 | B8: Motor | C8: 2 | D8: Emax XA2212 980 KV (original) | E8: 3S; ≈ 880 g thrust with 10-inch prop; branded, better quality control; ≈ 90 g | F8: 1345 | G8: In stock | H8: https://zbotic.in/product/xa2212-980kv-outrunner-brushless-dc-motor/ | I8: Listing
A9: ES1 | B9: ESC | C9: 1 | D9: SimonK 30 A ESC | E9: 30 A continuous, 2–3S, BEC 5 V / 3 A | F9: 499 | G9: In stock | H9: https://probots.co.in/simonk-30a-bldc-esc-electronic-speed-controller-with-connectors.html | I9: Listing
A10: ES2 | B10: ESC | C10: 2 | D10: Brushless 40 A ESC | E10: 40 A continuous, 60 A burst, 2–4S, BEC 5 V / 3 A, 34 g | F10: 1038 | G10: Out of stock (25–30 days) | H10: https://st.robu.in/?p=1289668 | I10: Listing
A11: PR1 | B11: Propeller (pair) | C11: 1 | D11: 1045 propeller (10 × 4.5 in) | E11: Plastic, 1 CW + 1 CCW; tractor plane uses one | F11: 105 | G11: In stock | H11: https://probots.co.in/black-1045-blade-propeller-10-inch-10x4-5-pair.html | I11: Listing
A12: PR2 | B12: Propeller (pair) | C12: 2 | D12: Emax 1045 ABS propeller | E12: Branded, better balanced; 1 CW + 1 CCW | F12: 265 | G12: In stock | H12: https://st.robu.in/product/emax-104510x4-5-abs-propellers-black-1cw1ccw | I12: Listing
A13: BA1 | B13: Battery | C13: 1 | D13: Orange 3S 2200 mAh 40C LiPo | E13: 11.1 V, 175 g, 40C (88 A), XT60 + JST-XH | F13: 1444 | G13: Out of stock | H13: https://st.robu.in/?p=30983 | I13: Listing
A14: BA2 | B14: Battery | C14: 2 | D14: Orange 3S 1800 mAh 40C LiPo | E14: 11.1 V, 168 g, 40C (72 A), XT60 + JST-XH | F14: 1599 | G14: In stock | H14: https://stg.robu.in/?p=32012 | I14: Listing
A15: SV1 | B15: Servo | C15: 1 | D15: SG90 9 g micro servo | E15: Plastic gears, 1.6–1.8 kg·cm, 9 g | F15: 119 | G15: In stock | H15: https://probots.co.in/mini-servo-motor-sg90-for-arduino-rc-planes-9g-9-gram.html | I15: Listing
A16: SV2 | B16: Servo | C16: 2 | D16: MG90S metal-gear micro servo | E16: Metal gears, ≈ 2.2 kg·cm at 6 V, 13.4 g | F16: 179 | G16: Out of stock | H16: https://probots.co.in/mini-servo-motor-mg90s-metal-gear-for-arduino-rc-planes.html | I16: Listing
... A30: TA1 | B30: Tape | C30: 1 | D30: Packing / fibre tape | E30: Hinges and reinforcement | F30: 100 | G30: Local | H30: — | I30: Estimate
A31: SH1 | B31: Shipping | C31: 1 | D31: Delivery to Mandi (≈ 2 orders) | F31: 150 | G31: — | H31: — | I31: Estimate

Sheet Configurations
A1: P4 — Budget vs Performance Configurations
A2: Unit prices link to the Component Options tab (green). Quantities in blue can be changed.
A4: Component | B4: Budget: choice | C4: Qty | D4: Unit (₹) | E4: Total (₹) | F4: Performance: choice | G4: Qty | H4: Unit (₹) | I4: Total (₹)
A5: Transmitter + receiver | B5: FlySky CT6B + FS-R6B | C5: 1 | D5: ='Component Options'!$F$6 -> 2413 | E5: =C5*D5 -> 2413 | F5: FlySky FS-i6 + FS-iA6B | G5: 1 | H5: ='Component Options'!$F$5 -> 4999 | I5: =G5*H5 -> 4999
A6: Motor | B6: A2212 1000 KV outrunner | C6: 1 | D6: ='Component Options'!$F$7 -> 383 | E6: =C6*D6 -> 383 | F6: Emax XA2212 980 KV (original) | G6: 1 | H6: ='Component Options'!$F$8 -> 1345 | I6: =G6*H6 -> 1345
A7: ESC | B7: SimonK 30 A ESC | C7: 1 | D7: ='Component Options'!$F$9 -> 499 | E7: =C7*D7 -> 499 | F7: Brushless 40 A ESC | G7: 1 | H7: ='Component Options'!$F$10 -> 1038 | I7: =G7*H7 -> 1038
A8: Propeller (pairs) | B8: 1045 propeller (10 × 4.5 in) | C8: 1 | D8: ='Component Options'!$F$11 -> 105 | E8: =C8*D8 -> 105 | F8: Emax 1045 ABS propeller | G8: 1 | H8: ='Component Options'!$F$12 -> 265 | I8: =G8*H8 -> 265
A9: Battery | B9: Orange 3S 2200 mAh 40C LiPo | C9: 1 | D9: ='Component Options'!$F$13 -> 1444 | E9: =C9*D9 -> 1444 | F9: Orange 3S 2200 mAh 40C LiPo | G9: 2 | H9: ='Component Options'!$F$13 -> 1444 | I9: =G9*H9 -> 2888
A10: Servos | B10: SG90 9 g micro servo | C10: 4 | D10: ='Component Options'!$F$15 -> 119 | E10: =C10*D10 -> 476 | F10: MG90S metal-gear micro servo | G10: 4 | H10: ='Component Options'!$F$16 -> 179 | I10: =G10*H10 -> 716
A11: Charger | B11: IMAX B3 Pro compact charger | C11: 1 | D11: ='Component Options'!$F$18 -> 499 | E11: =C11*D11 -> 499 | F11: IMAX B6AC balance charger | G11: 1 | H11: ='Component Options'!$F$17 -> 3499 | I11: =G11*H11 -> 3499
A12: Pushrods | B12: Z-type steel pushrod 1.2 × 260 mm (pack of 2) | C12: 2 | D12: ='Component Options'!$F$19 -> 146 | E12: =C12*D12 -> 292 | F12: M3 stainless servo linkage rod 200 mm | G12: 4 | H12: ='Component Options'!$F$20 -> 249 | I12: =G12*H12 -> 996
A13: Wing spar | B13: Carbon fibre tube 6 × 4 × 500 mm (pack of 2) | C13: 1 | D13: ='Component Options'!$F$21 -> 299 | E13: =C13*D13 -> 299 | F13: Carbon fibre tube 6 × 4 × 500 mm (pack of 2) | G13: 1 | H13: ='Component Options'!$F$21 -> 299 | I13: =G13*H13 -> 299
A14: Control horns (packs) | B14: Nylon control horn (pack of 2 + screws) | C14: 2 | D14: ='Component Options'!$F$22 -> 49 | E14: =C14*D14 -> 98 | F14: Nylon control horn (pack of 2 + screws) | G14: 2 | H14: ='Component Options'!$F$22 -> 49 | I14: =G14*H14 -> 98
A15: Servo extension leads | B15: Servo extension 30 cm | C15: 2 | D15: ='Component Options'!$F$23 -> 95 | E15: =C15*D15 -> 190 | F15: Servo extension 30 cm | G15: 2 | H15: ='Component Options'!$F$23 -> 95 | I15: =G15*H15 -> 190
A16: XT60 pairs | B16: XT60 male + female pair | C16: 2 | D16: ='Component Options'!$F$24 -> 39 | E16: =C16*D16 -> 78 | F16: XT60 male + female pair | G16: 2 | H16: ='Component Options'!$F$24 -> 39 | I16: =G16*H16 -> 78
A17: LiPo safety bag | B17: Fire-resistant LiPo bag 220 × 100 × 75 mm | C17: 1 | D17: ='Component Options'!$F$25 -> 659 | E17: =C17*D17 -> 659 | F17: Fire-resistant LiPo bag 220 × 100 × 75 mm | G17: 1 | H17: ='Component Options'!$F$25 -> 659 | I17: =G17*H17 -> 659
A18: Foam board sheets | B18: 5 mm paper-faced foam board, 20 × 30 in | C18: 4 | D18: ='Component Options'!$F$26 -> 120 | E18: =C18*D18 -> 480 | F18: 5 mm paper-faced foam board, 20 × 30 in | G18: 4 | H18: ='Component Options'!$F$26 -> 120 | I18: =G18*H18 -> 480
A19: Wheels (pair) | B19: ≈ 50 mm RC plane wheels | C19: 1 | D19: ='Component Options'!$F$27 -> 300 | E19: =C19*D19 -> 300 | F19: ≈ 50 mm RC plane wheels | G19: 1 | H19: ='Component Options'!$F$27 -> 300 | I19: =G19*H19 -> 300
A20: Landing gear wire | B20: Steel wire ≈ 2 mm, bent to shape | C20: 1 | D20: ='Component Options'!$F$28 -> 100 | E20: =C20*D20 -> 100 | F20: Steel wire ≈ 2 mm, bent to shape | G20: 1 | H20: ='Component Options'!$F$28 -> 100 | I20: =G20*H20 -> 100
A21: Hot glue gun + sticks | B21: Hot glue gun with sticks | C21: 1 | D21: ='Component Options'!$F$29 -> 350 | E21: =C21*D21 -> 350 | F21: Hot glue gun with sticks | G21: 1 | H21: ='Component Options'!$F$29 -> 350 | I21: =G21*H21 -> 350
A22: Tape | B22: Packing / fibre tape | C22: 1 | D22: ='Component Options'!$F$30 -> 100 | E22: =C22*D22 -> 100 | F22: Packing / fibre tape | G22: 1 | H22: ='Component Options'!$F$30 -> 100 | I22: =G22*H22 -> 100
A23: Shipping | B23: Delivery to Mandi (≈ 2 orders) | C23: 1 | D23: ='Component Options'!$F$31 -> 150 | E23: =C23*D23 -> 150 | F23: Delivery to Mandi (≈ 2 orders) | G23: 1 | H23: ='Component Options'!$F$31 -> 150 | I23: =G23*H23 -> 150
A24: Total build cost | E24: =SUM(E5:E23) -> 8915 | I24: =SUM(I5:I23) -> 18550
A25: Difference (Performance − Budget) | I25: =I24-E24 -> 9635
A28: Chosen for Techfest 2026
A29: Budget build with the radio upgraded to the FlySky FS-i6 (on-radio failsafe setup).
A30: Budget total | E30: =E24 -> 8915
A31: − CT6B radio + FS-i6 radio | E31: =I5-E5 -> 2586
A32: Chosen build total | E32: =E30+E31 -> 11501
A35: Upgrade order if more budget becomes available
A36: 1. Second 3S 2200 mAh battery | B36: More flights per test session | C36: 1 | D36: ='Component Options'!$F$13 -> 1444 | E36: =C36*D36 -> 1444
A37: 2. IMAX B6AC charger instead of B3 | B37: Charges at 1C (≈ 1 h) instead of 0.8 A (≈ 3 h) | C37: 1 | D37: ='Component Options'!$F$17 -> 3499 | E37: =C37*D37-'Component Options'!$F$18 -> 3000
A38: 3. MG90S servos instead of SG90 | B38: Metal gears survive crashes | C38: 4 | D38: ='Component Options'!$F$16 -> 179 | E38: =C38*(D38-'Component Options'!$F$15) -> 240
A39: Extra cost of all three upgrades | E39: =SUM(E36:E38) -> 4684

Sheet Engineering Checks
A1: P4 — Propulsion, Electrical and Mass Checks (chosen build)
A2: Blue = input (source in column D). Black = formula. Pass/fail cells compare a result with its limit.
A4: Quantity | B4: Value | C4: Unit | D4: Source / formula
A5: Battery nominal voltage | B5: 11.1 | C5: V | D5: 3S × 3.7 V
A6: Motor KV | B6: 1000 | C6: RPM/V | D6: A2212 1000 KV listing
A7: Propeller pitch | B7: 4.5 | C7: in | D7: 1045 propeller
A8: Static thrust at full throttle | B8: 885 | C8: g | D8: Thingbits A2212 1000 KV table: 1047 prop, 11.1 V (1045 gives slightly less)
A9: Current at full throttle | B9: 15.6 | C9: A | D9: Same table
A10: Electrical power at full throttle | B10: 173 | C10: W | D10: Same table
A11: All-up mass | B11: ='Weight Build-up'!$E$33 -> 1144.3473 | C11: g | D11: Linked from the Weight Build-up tab
A12: Wing area | B12: 0.29 | C12: m² | D12: Design value (P3 sizing)
A13: Maximum lift coefficient C_L,max | B13: 1.2 | C13: — | D13: Assumed for a flat-bottom trainer wing
A14: Air density | B14: 1.225 | C14: kg/m³ | D14: Sea level (Mumbai)
A15: ESC continuous rating | B15: 30 | C15: A | D15: SimonK 30 A listing
A16: Required ESC margin | B16: 1.2 | C16: × | D16: Design rule: rating ≥ 1.2 × max current
A17: Battery capacity | B17: 2.2 | C17: Ah | D17: Orange 3S 2200 mAh
A18: Battery C-rating | B18: 40 | C18: C | D18: Orange listing
A19: Usable battery fraction | B19: 0.8 | C19: — | D19: Assumed: land at 20% charge left to protect the LiPo
A20: BEC rating | B20: 3 | C20: A | D20: SimonK 30 A listing (5 V / 3 A)
A21: Number of servos | B21: 4 | C21: — | D21: 2 ailerons, elevator, rudder
A22: Current per servo while moving | B22: 0.25 | C22: A | D22: Typical for 9 g servos — check datasheet
A23: Receiver current | B23: 0.1 | C23: A | D23: Typical — check datasheet
A24: Minimum thrust-to-weight | B24: 0.5 | C24: — | D24: Trainer guideline
A26: Results
A27: Check | B27: Result | C27: Unit | D27: Formula | E27: Limit | F27: Pass?
A28: No-load motor speed | B28: =$B$6*$B$5 -> 11100 | C28: RPM | D28: RPM = KV × V
A29: No-load pitch speed | B29: =B28*$B$7*0.0254/60 -> 21.1455 | C29: m/s | D29: V_pitch = RPM × pitch × 0.0254 ÷ 60
A30: Stall speed | B30: =SQRT(2*$B$11/1000*9.81/($B$14*$B$12*$B$13)) -> 7.257228 | C30: m/s | D30: V_stall = √(2W ÷ ρ S C_L,max)
A31: Pitch speed ÷ stall speed | B31: =B29/B30 -> 2.9137158 | C31: × | D31: ratio | E31: ≥ 2 | F31: =IF(B31>=2,"PASS","CHECK") -> PASS
A32: Thrust-to-weight | B32: =$B$8/$B$11 -> 0.77336659 | C32: — | D32: T/W = thrust ÷ weight | E32: =$B$24 -> 0.5 | F32: =IF(B32>=E32,"PASS","FAIL") -> PASS
A33: Power-to-weight | B33: =$B$10/($B$11/1000) -> 151.17788 | C33: W/kg | D33: P ÷ m
A34: ESC margin | B34: =$B$15/$B$9 -> 1.9230769 | C34: × | D34: I_ESC ÷ I_max | E34: =$B$16 -> 1.2 | F34: =IF(B34>=E34,"PASS","FAIL") -> PASS
A35: Battery maximum current | B35: =$B$18*$B$17 -> 88 | C35: A | D35: I_max = C × capacity | E35: =$B$9 -> 15.6 | F35: =IF(B35>=E35,"PASS","FAIL") -> PASS
A36: Battery energy | B36: =$B$5*$B$17 -> 24.42 | C36: Wh | D36: E = V × Ah | E36: ≤ 100 Wh (airline) | F36: =IF(B36<=100,"PASS","FAIL") -> PASS
A37: Flight time at full throttle (minimum) | B37: =$B$17*$B$19/$B$9*60 -> 6.7692308 | C37: min | D37: t = Ah × usable ÷ I × 60
A38: BEC load | B38: =$B$21*$B$22+$B$23 -> 1.1 | C38: A | D38: n × I_servo + I_rx | E38: =$B$20 -> 3 | F38: =IF(B38<=E38,"PASS","FAIL") -> PASS

Sheet Weight Build-up
A1: RC Aircraft Weight Build-up
A2: Bottom-up estimate of the all-up weight. Blue = input, black = formula, green = linked input.
A4: Inputs
A5: Payload (g) | B5: 300 | C5: Assumed mission payload (not from the Techfest rulebook)
A6: Design all-up weight (g) | B6: 1200 | C6: Calculated all-up weight rounded up for build margin
A7: Spar outer diameter (mm) | B7: 6 | C7: 6 × 4 mm pultruded carbon tube (Robu listing)
A8: Spar inner diameter (mm) | B8: 4 | C8: Robu listing
A9: Spar length (mm) | B9: 1000 | C9: Two 500 mm tubes
A10: Carbon fibre density (g/cm³) | B10: 1.55 | C10: Typical for pultruded carbon fibre
A11: Foam board sheet weight (g per 20×30 in sheet) | B11: 140 | C11: Estimate for paper-faced foam board; weigh one sheet to confirm
A12: Foam sheets used | B12: 2.5 | C12: Wing ≈ 1.5 sheets + fuselage and tail ≈ 1 sheet
A14: Spar cross-section area (mm²) | B14: =PI()/4*($B$7^2-$B$8^2) -> 15.707963
A15: Spar mass (g) | B15: =B14*$B$9/1000*$B$10 -> 24.347343 | C15: area × length ÷ 1000 × density
A17: Part | B17: Category | C17: Qty | D17: Unit weight (g) | E17: Total weight (g) | F17: % of empty weight | G17: Confidence | H17: Source / notes
A18: 3S 2200 mAh 40C LiPo battery | B18: Electronics & battery | C18: 1 | D18: 175 | E18: =C18*D18 -> 175 | F18: =E18/$E$31 -> 0.20726067 | G18: Listing | H18: Robu listing, 175 g
A19: SG90 9 g servo | B19: Electronics & battery | C19: 4 | D19: 9 | E19: =C19*D19 -> 36 | F19: =E19/$E$31 -> 0.042636482 | G19: Listing | H19: Probots listing, 9 g each
A20: A2212 1000 KV motor | B20: Electronics & battery | C20: 1 | D20: 52 | E20: =C20*D20 -> 52 | F20: =E20/$E$31 -> 0.061586029 | G20: Typical | H20: Thingbits listing ≈ 52 g
A21: 30 A ESC | B21: Electronics & battery | C21: 1 | D21: 25 | E21: =C21*D21 -> 25 | F21: =E21/$E$31 -> 0.029608668 | G21: Typical | H21: Typical spec
A22: FS-iA6B receiver | B22: Electronics & battery | C22: 1 | D22: 15 | E22: =C22*D22 -> 15 | F22: =E22/$E$31 -> 0.017765201 | G22: Typical | H22: Typical spec
A23: 1045 propeller | B23: Electronics & battery | C23: 1 | D23: 12 | E23: =C23*D23 -> 12 | F23: =E23/$E$31 -> 0.014212161 | G23: Typical | H23: Typical spec
A24: Carbon fibre spar 6×4 mm | B24: Structure | C24: 1 | D24: =B15 -> 24.347343 | E24: =C24*D24 -> 24.347343 | F24: =E24/$E$31 -> 0.028835696 | G24: Calculated | H24: From spar inputs above
A25: Foam board (paper-faced, 5 mm) | B25: Structure | C25: =$B$12 -> 2.5 | D25: =$B$11 -> 140 | E25: =C25*D25 -> 350 | F25: =E25/$E$31 -> 0.41452135 | G25: Estimate | H25: Avoid PVC sunboard — much heavier
A26: Hot glue | B26: Hardware & assembly | C26: 1 | D26: 50 | E26: =C26*D26 -> 50 | F26: =E26/$E$31 -> 0.059217336 | G26: Estimate
A27: Landing gear (steel wire) | B27: Hardware & assembly | C27: 1 | D27: 40 | E27: =C27*D27 -> 40 | F27: =E27/$E$31 -> 0.047373869 | G27: Estimate
A28: Wires and XT60 connectors | B28: Hardware & assembly | C28: 1 | D28: 30 | E28: =C28*D28 -> 30 | F28: =E28/$E$31 -> 0.035530401 | G28: Estimate
A29: Control horns and pushrods | B29: Hardware & assembly | C29: 1 | D29: 15 | E29: =C29*D29 -> 15 | F29: =E29/$E$31 -> 0.017765201 | G29: Estimate
A30: Tape | B30: Hardware & assembly | C30: 1 | D30: 20 | E30: =C30*D30 -> 20 | F30: =E30/$E$31 -> 0.023686934 | G30: Estimate
A31: Empty weight | E31: =SUM(E18:E30) -> 844.34734
A32: Payload | E32: =$B$5 -> 300
A33: All-up weight (calculated) | E33: =E31+E32 -> 1144.3473
A34: Design weight used for sizing | E34: =$B$6 -> 1200
A35: Margin for build errors (g) | E35: =E34-E33 -> 55.652657
A36: Margin (% of design weight) | E36: =IF(E34=0,0,E35/E34) -> 0.046377214
A39: Summary by category
A40: Category | B40: Weight (g) | C40: % of empty weight
A41: Electronics & battery | B41: =SUMIF($B$18:$B$30,A41,$E$18:$E$30) -> 315 | C41: =B41/$E$31 -> 0.37306921
A42: Structure | B42: =SUMIF($B$18:$B$30,A42,$E$18:$E$30) -> 374.34734 | C42: =B42/$E$31 -> 0.44335705
A43: Hardware & assembly | B43: =SUMIF($B$18:$B$30,A43,$E$18:$E$30) -> 155 | C43: =B43/$E$31 -> 0.18357374
